align_trim/__init__.py
align_trim/main.py
align_trim-1.0.2.dist-info/METADATA
align_trim-1.0.2.dist-info/WHEEL
align_trim-1.0.2.dist-info/entry_points.txt
align_trim-1.0.2.dist-info/licenses/LICENSE
align_trim-1.0.2.dist-info/RECORD
