Metadata-Version: 2.4
Name: align_trim
Version: 1.0.2
Summary: Soft-clip primer sites for SAM/BAM files generated from amplicon sequencing runs
Project-URL: Repository, https://github.com/artic-network/align_trim.git
Project-URL: Issues, https://github.com/artic-network/align_trim/issues
Author-email: Nick Loman <n.j.loman@bham.ac.uk>, Sam Wilkinson <s.a.j.wilkinson@bham.ac.uk>, Chris Kent <c.g.kent@bham.ac.uk>
Maintainer-email: Sam Wilkinson <s.a.j.wilkinson@bham.ac.uk>, Chris Kent <c.g.kent@bham.ac.uk>
License-Expression: MIT
License-File: LICENSE
Requires-Python: >=3.9
Requires-Dist: numpy
Requires-Dist: primalbedtools>=0.10.1
Requires-Dist: pysam
